littlefluffyclouds/__init__.py
littlefluffyclouds-0.2.0.dist-info/METADATA
littlefluffyclouds-0.2.0.dist-info/WHEEL
littlefluffyclouds-0.2.0.dist-info/entry_points.txt
littlefluffyclouds-0.2.0.dist-info/licenses/LICENSE
littlefluffyclouds-0.2.0.dist-info/RECORD
