Metadata-Version: 2.4
Name: littlefluffyclouds
Version: 0.2.0
Summary: Gather a bunch of small adjacent networks into larger ones.
Project-URL: Homepage, https://github.com/kstrauser/littlefluffyclouds
Project-URL: Repository, https://github.com/kstrauser/littlefluffyclouds.git
Project-URL: Issues, https://github.com/kstrauser/littlefluffyclouds/issues
Author-email: Kirk Strauser <kirk@strauser.com>
License-Expression: GPL-3.0-or-later
License-File: LICENSE
Classifier: Development Status :: 4 - Beta
Classifier: Environment :: Console
Classifier: Intended Audience :: Developers
Classifier: Intended Audience :: System Administrators
Classifier: License :: OSI Approved :: GNU General Public License v3 or later (GPLv3+)
Classifier: Operating System :: OS Independent
Classifier: Programming Language :: Python :: 3
Classifier: Topic :: Internet
Classifier: Topic :: Security
Classifier: Topic :: System :: Networking
Classifier: Topic :: Utilities
Requires-Python: >=3.13
